bayalign/__init__.py
bayalign/inference.py
bayalign/kdtree.py
bayalign/pointcloud.py
bayalign/score.py
bayalign/sphere_tesselation.py
bayalign/sphere_utils.py
bayalign/types.py
bayalign/utils.py
bayalign-0.1.2.dist-info/licenses/LICENSE
bayalign-0.1.2.dist-info/METADATA
bayalign-0.1.2.dist-info/WHEEL
bayalign-0.1.2.dist-info/top_level.txt
bayalign-0.1.2.dist-info/RECORD
