Metadata-Version: 2.4
Name: bayalign
Version: 0.1.2
Summary: Bayesian inference for 3D-2D rigid registration written in JAX.
Requires-Python: >=3.10
License-File: LICENSE
Requires-Dist: jax>=0.6.0
Requires-Dist: jaxtyping>=0.3.2
Requires-Dist: joblib>=1.5.0
Requires-Dist: numpy>=2.2.5
Provides-Extra: examples
Requires-Dist: scipy>=1.15.2; extra == "examples"
Requires-Dist: arviz>=0.21.0; extra == "examples"
Requires-Dist: corner>=2.2.3; extra == "examples"
Requires-Dist: matplotlib>=3.10.1; extra == "examples"
Requires-Dist: mrcfile>=1.5.4; extra == "examples"
Requires-Dist: pandas>=2.2.3; extra == "examples"
Requires-Dist: plotly>=6.0.1; extra == "examples"
Requires-Dist: scikit-image>=0.25.2; extra == "examples"
Requires-Dist: seaborn>=0.13.2; extra == "examples"
Requires-Dist: nbformat>=5.10.4; extra == "examples"
Requires-Dist: h5py>=3.13.0; extra == "examples"
Provides-Extra: dev
Requires-Dist: ruff>=0.11.8; extra == "dev"
Requires-Dist: ipykernel>=6.29.5; extra == "dev"
Provides-Extra: all
Requires-Dist: bayalign[dev,examples]; extra == "all"
Dynamic: license-file
